{
  "timestamp": "2025-10-15T11:49:12.882344",
  "vantage_point": "itaiwan",
  "target": "www2.judicial.gov.tw",
  "target_ip": "210.69.124.99",
  "protocol": "tcp",
  "port": 443,
  "duration_seconds": 0.02,
  "hops": [],
  "num_hops": 0,
  "success": false,
  "path_analysis": {
    "networks_traversed": [],
    "interesting_routers": [],
    "private_hops": 0,
    "total_hops": 0,
    "network_transitions": []
  },
  "raw_output": "",
  "category": "government_critical",
  "base_domain": "judicial.gov.tw",
  "service_variant": "www2.judicial.gov.tw",
  "is_bare_domain": false
}